weather_forecast_cli_dotnetthoughts/__init__.py
weather_forecast_cli_dotnetthoughts/app.py
weather_forecast_cli_dotnetthoughts-1.0.0.dist-info/METADATA
weather_forecast_cli_dotnetthoughts-1.0.0.dist-info/WHEEL
weather_forecast_cli_dotnetthoughts-1.0.0.dist-info/licenses/LICENSE
weather_forecast_cli_dotnetthoughts-1.0.0.dist-info/RECORD
