Metadata-Version: 2.1
Name: weather_forecast_cli_dotnetthoughts
Version: 1.0.0
Summary: Weatherforecast CLI tool
Project-URL: Homepage, https://github.com/Fastest-Coder-First/Python-Weather-Forecasting-Tool
Project-URL: Bug Tracker, https://github.com/Fastest-Coder-First/Python-Weather-Forecasting-Tool/issues
Author-email: Anuraj <anuraj@dotnetthoughts.net>
License-File: LICENSE
Classifier: License :: OSI Approved :: MIT License
Classifier: Operating System :: OS Independent
Classifier: Programming Language :: Python :: 3
Requires-Python: >=3.7
